chathon/__init__.py
chathon/bot.py
chathon/client.py
chathon/server.py
chathon-2.2.dist-info/LICENSE
chathon-2.2.dist-info/METADATA
chathon-2.2.dist-info/WHEEL
chathon-2.2.dist-info/top_level.txt
chathon-2.2.dist-info/RECORD
