Metadata-Version: 2.1
Name: chathon
Version: 2.2
Summary: A Python Packages to make own chat room
Home-page: https://github.com/EterNomm/Chathon
Author: LyQuid
Author-email: lyquidpersonal@gmail.com
License: Apache License 2.0
Project-URL: Discord, https://discord.gg/qpT2AeYZRN
Project-URL: Issue tracker, https://github.com/EterNomm/Chathon/issues
Keywords: python,chathon,chat,chat room,chat app,chat bot
Platform: UNKNOWN
Classifier: Development Status :: 5 - Production/Stable
Classifier: Intended Audience :: Developers
Classifier: License :: OSI Approved :: Apache Software License
Classifier: Operating System :: Android
Classifier: Operating System :: Microsoft :: Windows
Classifier: Operating System :: MacOS
Classifier: Operating System :: POSIX :: Linux
Classifier: Programming Language :: Python
License-File: LICENSE
Requires-Dist: colorgb
Requires-Dist: better-profanity (==0.7.0)
